{
  "TS": "2025-07-23 15:54:34.7128",
  "CODE": "SalesforceRequest",
  "LOGGER": "SalesforceRestClient",
  "LEVEL": "Info",
  "Count": "1",
  "Data": [
    {
      "Opportunity": {
        "RB_Fields": {
          "DonorRole": "Donor",
          "GiftType": "One Time Gift",
          "PaymentProcessor": "NeonPay",
          "ProcessorTransactionId": "npcharge_112b28949cafd28c129b42adea91a318",
          "Authorization": "t1_txn_68813def04573865207266c",
          "CcNumber": "************1111",
          "CcCardType": "Visa",
          "ExpMonth": "12",
          "ExpYear": "2032",
          "PaymentRecordType": "Credit Card",
          "PaymentType": "Credit Card",
          "CurrencyIsoCode": "USD",
          "IsCompanyDonation": false,
          "NameOnPaymentMethod": "reg no1"
        },
        "RB_Objects": {
          "Donor": {
            "RB_Fields": {
              "CampaignMemberId": "3:2325",
              "MainFieldsSubmitted": true,
              "AddressSubmitted": true,
              "CustomFieldsSubmitted": true,
              "RemoveOnUpdate": [
                "LeadSource"
              ]
            },
            "RB_Objects": {
              "Account": {
                "RB_Fields": {},
                "RB_Objects": {},
                "account__c": "a"
              },
              "CampaignMember": {
                "RB_Fields": {},
                "RB_Objects": {},
                "rallybound__Is_Donor__c": true,
                "campaignMember__c": "a",
                "campaignMember_donor__c": "a"
              }
            },
            "FirstName": "reg",
            "LastName": "no1",
            "Email": "regnodonation@example.com",
            "MailingStreet": "1 Roadville Road",
            "MailingCity": "Roadville",
            "MailingState": "IL",
            "MailingPostalCode": "11111",
            "MailingCountry": "UNITED STATES",
            "rallybound__Member_ID__c": 2325,
            "rallybound__User_Account_ID__c": 1002251,
            "contact_field__c": "a"
          },
          "Campaign": {
            "RB_Fields": {},
            "RB_Objects": {
              "ParentCampaign": {
                "RB_Fields": {},
                "RB_Objects": {},
                "rallybound__RallyBound_GoalID__c": 1007
              }
            },
            "Name": "my fundraising campaign",
            "Type": "Peer-to-peer member",
            "Status": "In Progress",
            "ExpectedRevenue": 100,
            "rallybound__RallyBound_GoalID__c": 2058,
            "rallybound__RallyBound_Personal_Page__c": "https://simple.rallybound.dev/campaign1010101",
            "campaign_member__c": "a"
          },
          "OpportunityLineItems": [
            {
              "RB_Fields": {},
              "PricebookEntryId": "hij",
              "Description": "Registration - reg no1",
              "Quantity": 1,
              "UnitPrice": 5,
              "lineitem__c": "a"
            }
          ]
        },
        "Name": "SimplePlatform Registrations",
        "Description": "",
        "Amount": 5,
        "CloseDate": "U2025-07-23 19:54:00",
        "StageName": "Closed Won",
        "rallybound__RallyBound_PaymentID__c": 2428,
        "donation_field__c": "a"
      },
      "QueueId": 1151,
      "Action": "syncDonation",
      "Settings": {
        "SalesforceType": 2,
        "UseStateCode": false,
        "OverwriteAddress": false,
        "ContactFindModeType": 1,
        "SoftCreditRole": "Soft Credit",
        "TributeNotifyRole": "Honor",
        "Type": 3,
        "CampaignID": 3,
        "UseBasicRecurringDonation": false,
        "UseAdvancedRecurringDonation": true,
        "CreateOrganizationAccounts": false,
        "AlwaysPushRsvpOnly": false,
        "AddRsvpOnlyToHousehold": false,
        "AddRsvpOnlyToHouseholdByName": false,
        "DebugMode": 4,
        "AllowNewObjOnSfMatchingFind": false,
        "OverwriteAccountName": false,
        "SetDonorAsPrimaryContactForCompanyDonations": false
      }
    }
  ]
}